cli.py
vibe_bridge-0.1.0.dist-info/METADATA
vibe_bridge-0.1.0.dist-info/WHEEL
vibe_bridge-0.1.0.dist-info/entry_points.txt
vibe_bridge-0.1.0.dist-info/top_level.txt
vibe_bridge-0.1.0.dist-info/RECORD
