Metadata-Version: 2.4
Name: vibe-bridge
Version: 0.1.0
Summary: Captures the 'why' behind code before you forget it.
Requires-Python: >=3.8
Requires-Dist: questionary
